setup.py
distributions_gaussian_binomial_nd/Binomialdistribution.py
distributions_gaussian_binomial_nd/Gaussiandistribution.py
distributions_gaussian_binomial_nd/Generaldistribution.py
distributions_gaussian_binomial_nd/__init__.py
distributions_gaussian_binomial_nd.egg-info/PKG-INFO
distributions_gaussian_binomial_nd.egg-info/SOURCES.txt
distributions_gaussian_binomial_nd.egg-info/dependency_links.txt
distributions_gaussian_binomial_nd.egg-info/not-zip-safe
distributions_gaussian_binomial_nd.egg-info/top_level.txt