Metadata-Version: 1.0
Name: distributions-gaussian-binomial-nd
Version: 0.1
Summary: Gaussian and Bionomial distributions
Home-page: UNKNOWN
Author: Nam Duong
Author-email: khanhnamdn91@gmail.com
License: UNKNOWN
Platform: UNKNOWN
